spark_test/__init__.py
spark_test/core/__init__.py
spark_test/core/azure_storage.py
spark_test/core/kyuubi.py
spark_test/core/pod.py
spark_test/core/s3.py
spark_test/fixtures/__init__.py
spark_test/fixtures/azure_storage.py
spark_test/fixtures/k8s.py
spark_test/fixtures/pod.py
spark_test/fixtures/s3.py
spark_test/fixtures/service_account.py
spark_test/resources/bin/microk8s.sh
spark_test/resources/bin/pod.sh
spark_test/resources/bin/s3.sh
spark_test/resources/python/test-iceberg.py
spark_test/resources/templates/podTemplate.yaml
spark_test/resources/templates/testpod.yaml
spark_test/utils.py
spark_k8s_test-0.0.4.dist-info/METADATA
spark_k8s_test-0.0.4.dist-info/WHEEL
spark_k8s_test-0.0.4.dist-info/RECORD
