Metadata-Version: 2.3
Name: spark-k8s-test
Version: 0.0.4
Summary: This project provides some utilities function and CLI commands to test Charmed Spark on K8s.
License: Apache-2.0
Author: Canonical Data Platform
Author-email: data-platform@lists.launchpad.net
Requires-Python: >=3.10,<4.0
Classifier: License :: OSI Approved :: Apache Software License
Classifier: Programming Language :: Python :: 3
Classifier: Programming Language :: Python :: 3.10
Classifier: Programming Language :: Python :: 3.11
Classifier: Programming Language :: Python :: 3.12
Classifier: Programming Language :: Python :: 3.13
Requires-Dist: azure-storage-blob (>=12.21.0,<13.0.0)
Requires-Dist: boto3 (>=1.36)
Requires-Dist: impyla (>=0.20.0,<0.21.0)
Requires-Dist: lightkube (>=0.11)
Requires-Dist: pytest (>=6.2)
Requires-Dist: spark8t (>=0.0.10)
